troveclient-stubs/__init__.pyi
troveclient-stubs/apiclient/__init__.pyi
troveclient-stubs/apiclient/auth.pyi
troveclient-stubs/apiclient/base.pyi
troveclient-stubs/apiclient/client.pyi
troveclient-stubs/auth_plugin.pyi
troveclient-stubs/base.pyi
troveclient-stubs/client.pyi
troveclient-stubs/common.pyi
troveclient-stubs/extension.pyi
troveclient-stubs/service_catalog.pyi
troveclient-stubs/shell.pyi
troveclient-stubs/utils.pyi
troveclient-stubs/v1/__init__.pyi
troveclient-stubs/v1/client.pyi
troveclient-stubs/v1/instances.pyi
python_troveclient_stubs-0.1.2.dist-info/LICENSE
python_troveclient_stubs-0.1.2.dist-info/METADATA
python_troveclient_stubs-0.1.2.dist-info/WHEEL
python_troveclient_stubs-0.1.2.dist-info/RECORD
